{"__symbolic":"module","version":4,"exports":[{"from":"./lib/user-controller"}],"metadata":{"ChangeDetectableComponentBase":{"__symbolic":"class","members":{"__ctor__":[{"__symbolic":"constructor","parameters":[{"__symbolic":"reference","module":"@angular/core","name":"ChangeDetectorRef","line":8,"character":43}]}],"markForCheck":[{"__symbolic":"method"}],"detach":[{"__symbolic":"method"}],"detectChanges":[{"__symbolic":"method"}],"checkNoChanges":[{"__symbolic":"method"}],"reattach":[{"__symbolic":"method"}]}},"CustomEncoder":{"__symbolic":"class","members":{"encodeKey":[{"__symbolic":"method"}],"encodeValue":[{"__symbolic":"method"}],"decodeKey":[{"__symbolic":"method"}],"decodeValue":[{"__symbolic":"method"}]}},"stringContains":{"__symbolic":"function","parameters":["value","search"],"value":{"__symbolic":"binop","operator":"!==","left":{"__symbolic":"call","expression":{"__symbolic":"select","expression":{"__symbolic":"call","expression":{"__symbolic":"select","expression":{"__symbolic":"reference","name":"value"},"member":"toLowerCase"}},"member":"indexOf"},"arguments":[{"__symbolic":"call","expression":{"__symbolic":"select","expression":{"__symbolic":"reference","name":"search"},"member":"toLowerCase"}}]},"right":-1}},"generateErrorMessage":{"__symbolic":"function","parameters":["message","httpError"],"value":{"__symbolic":"if","condition":{"__symbolic":"binop","operator":"&&","left":{"__symbolic":"binop","operator":"&&","left":{"__symbolic":"reference","name":"httpError"},"right":{"__symbolic":"select","expression":{"__symbolic":"reference","name":"httpError"},"member":"error"}},"right":{"__symbolic":"select","expression":{"__symbolic":"select","expression":{"__symbolic":"reference","name":"httpError"},"member":"error"},"member":"message"}},"thenExpression":{"__symbolic":"binop","operator":"+","left":{"__symbolic":"binop","operator":"+","left":{"__symbolic":"binop","operator":"+","left":{"__symbolic":"reference","name":"message"},"right":" ("},"right":{"__symbolic":"select","expression":{"__symbolic":"select","expression":{"__symbolic":"reference","name":"httpError"},"member":"error"},"member":"message"}},"right":")"},"elseExpression":{"__symbolic":"reference","name":"message"}}},"onlyUnique":{"__symbolic":"function","parameters":["value","index","self"],"value":{"__symbolic":"binop","operator":"===","left":{"__symbolic":"reference","name":"index"},"right":{"__symbolic":"call","expression":{"__symbolic":"select","expression":{"__symbolic":"reference","name":"self"},"member":"findIndex"},"arguments":[{"__symbolic":"error","message":"Lambda not supported","line":17,"character":6,"module":"./lib/utils"}]}}},"nameOf":{"__symbolic":"error","message":"Lambda not supported","line":22,"character":22,"module":"./lib/utils"},"flatMap":{"__symbolic":"function","parameters":["items","key"],"value":{"__symbolic":"call","expression":{"__symbolic":"select","expression":[],"member":"concat"},"arguments":[{"__symbolic":"spread","expression":{"__symbolic":"call","expression":{"__symbolic":"select","expression":{"__symbolic":"reference","name":"items"},"member":"map"},"arguments":[{"__symbolic":"error","message":"Lambda not supported","line":28,"character":43,"module":"./lib/utils"}]}}]}},"getZoneOffset":{"__symbolic":"function"},"getEnumKeys":{"__symbolic":"function","parameters":["enumType"],"value":{"__symbolic":"call","expression":{"__symbolic":"select","expression":{"__symbolic":"call","expression":{"__symbolic":"select","expression":{"__symbolic":"reference","name":"Object"},"member":"keys"},"arguments":[{"__symbolic":"reference","name":"enumType"}]},"member":"filter"},"arguments":[{"__symbolic":"error","message":"Lambda not supported","line":45,"character":4,"module":"./lib/utils"}]}},"isPropertyChanged":{"__symbolic":"function","parameters":["simpleChange"],"value":{"__symbolic":"binop","operator":"&&","left":{"__symbolic":"reference","name":"simpleChange"},"right":{"__symbolic":"binop","operator":"!==","left":{"__symbolic":"select","expression":{"__symbolic":"reference","name":"simpleChange"},"member":"previousValue"},"right":{"__symbolic":"select","expression":{"__symbolic":"reference","name":"simpleChange"},"member":"currentValue"}}}},"omitDeep":{"__symbolic":"function"},"getProgress":{"__symbolic":"function","parameters":["loaded","total"],"value":{"__symbolic":"call","expression":{"__symbolic":"select","expression":{"__symbolic":"reference","name":"Math"},"member":"round"},"arguments":[{"__symbolic":"binop","operator":"*","left":{"__symbolic":"binop","operator":"/","left":{"__symbolic":"reference","name":"loaded"},"right":{"__symbolic":"reference","name":"total"}},"right":100}]}}},"origins":{"ChangeDetectableComponentBase":"./lib/change-detectable-component-base","CustomEncoder":"./lib/custom-encoder","stringContains":"./lib/utils","generateErrorMessage":"./lib/utils","onlyUnique":"./lib/utils","nameOf":"./lib/utils","flatMap":"./lib/utils","getZoneOffset":"./lib/utils","getEnumKeys":"./lib/utils","isPropertyChanged":"./lib/utils","omitDeep":"./lib/utils","getProgress":"./lib/utils"},"importAs":"veritas-ui-library"}